{ "members": [{
    "name": "Al-Farouq Aminu",
    "position": "Forward",
    "number": "8",
    "description": "Coming soon",
    "picUrl": "http://ak-static.cms.nba.com/wp-content/uploads/headshots/nba/latest/260x190/202329.png"
  }, {
    "name": "Pat Connaughton",
    "position": "Guard-Forward",
    "number": "5",
    "description": "Coming soon",
    "picUrl": "http://ak-static.cms.nba.com/wp-content/uploads/headshots/nba/latest/260x190/1626192.png"
  }, {
    "name": "Allen Crabbe",
    "position": "Guard",
    "number": "23",
    "description": "Coming soon",
    "picUrl": "http://ak-static.cms.nba.com/wp-content/uploads/headshots/nba/latest/260x190/203459.png"
  }, {
    "name": "Ed Davis",
    "position": "Forward",
    "number": "17",
    "description": "Coming soon",
    "picUrl": "http://ak-static.cms.nba.com/wp-content/uploads/headshots/nba/latest/260x190/202334.png"
  }, {
    "name": "Festus Ezeli",
    "position": "Center",
    "number": "31",
    "description": "Coming soon",
    "picUrl": "http://ak-static.cms.nba.com/wp-content/uploads/headshots/nba/latest/260x190/203105.png"
  }, {
    "name": "Maurice Harkless",
    "position": "Forward",
    "number": "4",
    "description": "Coming soon",
    "picUrl": "http://ak-static.cms.nba.com/wp-content/uploads/headshots/nba/latest/260x190/203090.png"
  }, {
    "name": "Jake Layman",
    "position": "Forward",
    "number": "10",
    "description": "Coming soon",
    "picUrl": "http://ak-static.cms.nba.com/wp-content/uploads/headshots/nba/latest/260x190/1627774.png"
  }, {
    "name": "Meyers Leonard",
    "position": "Forward-Center",
    "number": "11",
    "description": "Coming soon",
    "picUrl": "http://ak-static.cms.nba.com/wp-content/uploads/headshots/nba/latest/260x190/203086.png"
  }, {
    "name": "Damian Lillard",
    "position": "Guard",
    "number": "0",
    "description": "Coming soon",
    "picUrl": "http://ak-static.cms.nba.com/wp-content/uploads/headshots/nba/latest/260x190/203081.png"
  }, {
    "name": "CJ Mccollum",
    "position": "Guard",
    "number": "3",
    "description": "Coming soon",
    "picUrl": "http://ak-static.cms.nba.com/wp-content/uploads/headshots/nba/latest/260x190/203468.png"
  }, {
    "name": "Shabazz Napier",
    "position": "Guard",
    "number": "6",
    "description": "Coming soon",
    "picUrl": "http://ak-static.cms.nba.com/wp-content/uploads/headshots/nba/latest/260x190/203894.png"
  }, {
    "name": "Jusuf Nurkic",
    "position": "Center",
    "number": "27",
    "description": "Coming soon",
    "picUrl": "http://ak-static.cms.nba.com/wp-content/uploads/headshots/nba/latest/260x190/203994.png"
  }, {
    "name": "Tim Quarterman",
    "position": "Guard",
    "number": "55",
    "description": "Coming soon",
    "picUrl": "http://ak-static.cms.nba.com/wp-content/uploads/headshots/nba/latest/260x190/1627817.png"
  }, {
    "name": "Noah Vonleh",
    "position": "Forward",
    "number": "21",
    "description": "Coming soon",
    "picUrl": "http://ak-static.cms.nba.com/wp-content/uploads/headshots/nba/latest/260x190/203943.png"
  }]
}
